valispace/__init__.py
valispace/example.py
valispace-0.1.24.1.dist-info/LICENSE
valispace-0.1.24.1.dist-info/METADATA
valispace-0.1.24.1.dist-info/WHEEL
valispace-0.1.24.1.dist-info/top_level.txt
valispace-0.1.24.1.dist-info/RECORD
