Metadata-Version: 2.1
Name: valispace
Version: 0.1.24.1
Summary: Valispace Python API
Home-page: https://github.com/valispace/ValispacePythonAPI
Author: Valispace
Author-email: support@valispace.com
License: MIT
Keywords: hardware engineering satellites rockets space technology
Platform: UNKNOWN
License-File: LICENSE
Requires-Dist: requests
Requires-Dist: six
